SurvivalPy-1.0.2.dist-info/DESCRIPTION.rst
SurvivalPy-1.0.2.dist-info/METADATA
SurvivalPy-1.0.2.dist-info/RECORD
SurvivalPy-1.0.2.dist-info/WHEEL
SurvivalPy-1.0.2.dist-info/metadata.json
SurvivalPy-1.0.2.dist-info/top_level.txt
survivalpy/__init__.py
survivalpy/logrank.py
survivalpy/survival.py
test/__init__.py
test/test_all.py
test/test_logrank.py
test/test_survival.py
