Metadata-Version: 2.0
Name: SurvivalPy
Version: 1.0.2
Summary: Kaplan-Meier Survival Plots and related statistics
Home-page: https://github.com/andricDu/SurvivalPy
Author: andricDu
Author-email: dusan.andric@oicr.on.ca
License: GPLv3
Keywords: survival analysis kaplan meier plot cancer
Platform: UNKNOWN
Requires: future
Requires: scipy
